tx_sendgrid_http_client/__init__.py
tx_sendgrid_http_client/client.py
tx_sendgrid_http_client/exceptions.py
tx_sendgrid_http_client-0.1.0.dist-info/METADATA
tx_sendgrid_http_client-0.1.0.dist-info/RECORD
tx_sendgrid_http_client-0.1.0.dist-info/WHEEL
tx_sendgrid_http_client-0.1.0.dist-info/top_level.txt
